NumberWrangler/Wrangler.py
NumberWrangler/__init__.py
NumberWrangler-0.0.2.dist-info/METADATA
NumberWrangler-0.0.2.dist-info/WHEEL
NumberWrangler-0.0.2.dist-info/top_level.txt
NumberWrangler-0.0.2.dist-info/RECORD
