Metadata-Version: 2.1
Name: NumberWrangler
Version: 0.0.2
Summary: Python package for slightly or massively variating numbers.
Home-page: https://github.com/aboombadev/NumberWrangler
Author: Abhay Shukla
Author-email: notsure@gmail.com
Classifier: Programming Language :: Python :: 3
Classifier: License :: OSI Approved :: GNU Affero General Public License v3
Classifier: Operating System :: OS Independent
Requires-Python: >=3.7
